akshare/__init__.py
akshare/datasets.py
akshare/exceptions.py
akshare/request.py
akshare/air/__init__.py
akshare/air/air_hebei.py
akshare/air/air_zhenqi.py
akshare/air/cons.py
akshare/air/crypto.js
akshare/air/outcrypto.js
akshare/air/sunrise_tad.py
akshare/article/__init__.py
akshare/article/cons.py
akshare/article/epu_index.py
akshare/article/ff_factor.py
akshare/article/fred_md.py
akshare/article/risk_rv.py
akshare/bank/__init__.py
akshare/bank/bank_cbirc_2020.py
akshare/bank/cons.py
akshare/bond/__init__.py
akshare/bond/bond_buy_back_em.py
akshare/bond/bond_cb_sina.py
akshare/bond/bond_cb_ths.py
akshare/bond/bond_cbond.py
akshare/bond/bond_china.py
akshare/bond/bond_china_money.py
akshare/bond/bond_convert.py
akshare/bond/bond_em.py
akshare/bond/bond_info_cm.py
akshare/bond/bond_issue_cninfo.py
akshare/bond/bond_nafmii.py
akshare/bond/bond_summary.py
akshare/bond/bond_zh_cov.py
akshare/bond/bond_zh_sina.py
akshare/bond/cons.py
akshare/cal/__init__.py
akshare/cal/rv.py
akshare/cost/__init__.py
akshare/cost/cost_living.py
akshare/crypto/__init__.py
akshare/crypto/crypto_bitcoin_cme.py
akshare/crypto/crypto_hold.py
akshare/currency/__init__.py
akshare/currency/currency.py
akshare/currency/currency_china_bank_sina.py
akshare/currency/currency_safe.py
akshare/data/__init__.py
akshare/data/cninfo.js
akshare/data/crypto_info.zip
akshare/data/ths.js
akshare/economic/__init__.py
akshare/economic/cons.py
akshare/economic/macro_australia.py
akshare/economic/macro_bank.py
akshare/economic/macro_canada.py
akshare/economic/macro_china.py
akshare/economic/macro_china_hk.py
akshare/economic/macro_china_nbs.py
akshare/economic/macro_constitute.py
akshare/economic/macro_euro.py
akshare/economic/macro_finance_ths.py
akshare/economic/macro_germany.py
akshare/economic/macro_info_ws.py
akshare/economic/macro_japan.py
akshare/economic/macro_other.py
akshare/economic/macro_swiss.py
akshare/economic/macro_uk.py
akshare/economic/macro_usa.py
akshare/economic/marco_cnbs.py
akshare_proxy-1.17.88.dist-info/LICENSE
akshare_proxy-1.17.88.dist-info/METADATA
akshare_proxy-1.17.88.dist-info/WHEEL
akshare_proxy-1.17.88.dist-info/top_level.txt
akshare_proxy-1.17.88.dist-info/RECORD
